devbio_napari/__init__.py
devbio_napari/__main__.py
devbio_napari/_viewer.py
devbio_napari-0.11.0.dist-info/LICENSE
devbio_napari-0.11.0.dist-info/METADATA
devbio_napari-0.11.0.dist-info/WHEEL
devbio_napari-0.11.0.dist-info/entry_points.txt
devbio_napari-0.11.0.dist-info/top_level.txt
devbio_napari-0.11.0.dist-info/RECORD
