Metadata-Version: 2.1
Name: devbio-napari
Version: 0.11.0
Summary: A bundle of napari plugins useful for 3D+t image processing and analysis for studying developmental biology.
Home-page: https://github.com/haesleinhuepf/devbio-napari
Author: Robert Haase
Author-email: robert.haase@uni-leipzig.de
License: BSD-3
Project-URL: Bug Tracker, https://github.com/haesleinhuepf/devbio-napari/issues
Project-URL: Documentation, https://github.com/haesleinhuepf/devbio-napari#README.md
Project-URL: Source Code, https://github.com/haesleinhuepf/devbio-napari
Project-URL: User Support, https://github.com/haesleinhuepf/devbio-napari/issues
Classifier: Development Status :: 3 - Alpha
Classifier: Intended Audience :: Science/Research
Classifier: Framework :: napari
Classifier: Programming Language :: Python
Classifier: Programming Language :: Python :: 3
Classifier: Programming Language :: Python :: 3.9
Classifier: Programming Language :: Python :: 3.10
Classifier: Programming Language :: Python :: 3.11
Classifier: Operating System :: OS Independent
Classifier: License :: OSI Approved :: BSD License
Requires-Python: >=3.9
License-File: LICENSE
Requires-Dist: napari-plugin-engine>=0.1.4
Requires-Dist: npe2
Requires-Dist: numpy>=1.21.4
Requires-Dist: napari-assistant>=0.4.9
Requires-Dist: napari-pyclesperanto-assistant>=0.23.0
Requires-Dist: napari-skimage-regionprops
Requires-Dist: napari-animation
Requires-Dist: PlatyMatch
Requires-Dist: napari-plot-profile
Requires-Dist: napari-accelerated-pixel-and-object-classification
Requires-Dist: napari-brightness-contrast
Requires-Dist: napari-plugin-search
Requires-Dist: napari-segment-blobs-and-things-with-membranes
Requires-Dist: napari-simpleitk-image-processing
Requires-Dist: napari-stl-exporter
Requires-Dist: napari-folder-browser
Requires-Dist: napari-crop
Requires-Dist: napari-clusters-plotter>=0.7.1
Requires-Dist: napari-tabu
Requires-Dist: napari-workflow-optimizer
Requires-Dist: napari-workflow-inspector
Requires-Dist: napari-curtain
Requires-Dist: napari-layer-details-display
Requires-Dist: napari
Requires-Dist: vispy
Requires-Dist: napari-mouse-controls
Requires-Dist: the-segmentation-game
Requires-Dist: napari-blob-detection
Requires-Dist: jupyterlab
Requires-Dist: napari-czifile2
Requires-Dist: napari-roi
Requires-Dist: pydantic!=1.10.0
Requires-Dist: napari-pystackreg
Requires-Dist: imageio!=2.22.1
Requires-Dist: redlionfish
Requires-Dist: jupyter-server
Requires-Dist: seaborn
